[{"id": "1098612433172582400", "url": "https://twitter.com/3xeoBHnoVv10WKp/status/1098612433172582400", "username": "", "text": "http://www. topicza.com/news87747.html ?d=21022019&f=69628 … เจ้าหน้าที่ โรยตัว ช่วยหมาจรจัด รอดตาย ตกบ่อน้ำร้าง กลางสวนยางภูเก็ต #ข่าวดารา #ข่าววันนี้ #ข่าวจริง #ข่าวช่องวัน #ข่าวPNC #ข่าวด่วน #ข่าว7HD", "date": "21-02-2019 22:56", "retweet": 0, "like": 0}, {"id": "1098611423540699136", "url": "https://twitter.com/3xeoBHnoVv10WKp/status/1098611423540699136", "username": "", "text": "http://www. topicza.com/news87746.html ?d=21022019&f=69628 … สลด! เจ้าทุยร้องไห้เป็นเลือด โดนรถชนขาหัก นอนกระอักอยู่ริมถนน #ข่าววันนี้ #ข่าวดารา #ข่าวจริง #ข่าวบันเทิง #ข่าวบันเทิง #ข่าวPNC #ข่าวด่วน #ข่าวบันเทิงวันนี้ #ข่าว7HD", "date": "21-02-2019 22:52", "retweet": 0, "like": 0}, {"id": "1097422869498277888", "url": "https://twitter.com/3xeoBHnoVv10WKp/status/1097422869498277888", "username": "", "text": "http://www. topicza.com/news87599.html ?d=18022019&f=69628 … ตีแผ่เบื้องหลัง ขอทานห้าง ตามตื๊อขอเงินบริจาค 10-20ไม่รับ ขอขั้นต่ำ 100 บาท เอายอดบริจาคเลี้ยงฉลองกินหรูหรา #ข่าวบันเทิงวันนี้ #ข่าว #ข่าววันนี้ #ข่าวจริง #ข่าวค่ํามิติใหม่ทั่วไทย #ข่าวดารา", "date": "18-02-2019 16:09", "retweet": 0, "like": 0}, {"id": "1097422521794609152", "url": "https://twitter.com/3xeoBHnoVv10WKp/status/1097422521794609152", "username": "", "text": "http://www. topicza.com/news87634.html ?d=18022019&f=69628 … ฮือฮา ผู้สมัคร ส.ส.สาว พรรคอนาคตใหม่ วัย 50 สวยเป๊ะ ปังแรง #ข่าว #ข่าวบันเทิง #ข่าวบันเทิงวันนี้ #ข่าววันนี้ #ข่าวช่อง8 #ข่าวจริง #ข่าวPNC #ข่าวจริงเช็กแล้ว #ข่าว7HD", "date": "18-02-2019 16:08", "retweet": 0, "like": 0}, {"id": "1097366054727106560", "url": "https://twitter.com/3xeoBHnoVv10WKp/status/1097366054727106560", "username": "", "text": "http://www. socialhot24.com/news87593.html ?d=18022019&f=69628 … สวดยับ! สาวจอดรถบนฟุตปาธขวางทางชาวบ้าน ซ้ำตั้งคำถาม ทำอะไร ? #ข่าว #ข่าวดารา #ข่าววันนี้ #ข่าวช่อง8 #ข่าวค่ํามิติใหม่ทั่วไทย #ข่าวด่วน #ข่าว7HD", "date": "18-02-2019 12:23", "retweet": 0, "like": 0}, {"id": "1097363599708717056", "url": "https://twitter.com/3xeoBHnoVv10WKp/status/1097363599708717056", "username": "", "text": "http://www. topicza.com/news87596.html ?d=18022019&f=69628 … ปลิวไปต่อหน้าต่อตา! พายุลมหมุนซัดตลาดนัดดังเมืองนางรอง #ข่าวบันเทิงวันนี้ #ข่าวดารา #ข่าว #ข่าวจริง #ข่าววันนี้ #ข่าวช่อง8 #ข่าวจริงเช็กแล้ว #ข่าว7HD", "date": "18-02-2019 12:14", "retweet": 0, "like": 0}, {"id": "1097363230307938304", "url": "https://twitter.com/3xeoBHnoVv10WKp/status/1097363230307938304", "username": "", "text": "http://www. topicza.com/news87599.html ?d=18022019&f=69628 … ตีแผ่เบื้องหลัง ขอทานห้าง ตามตื๊อขอเงินบริจาค 10-20ไม่รับ ขอขั้นต่ำ 100 บาท เอายอดบริจาคเลี้ยงฉลองกินหรูหรา #ข่าวบันเทิง #ข่าวบันเทิงวันนี้ #ข่าววันนี้ #ข่าวจริง #ข่าว7HD #ข่าวค่ํามิติใหม่ทั่วไทย #ข่าวช่องวัน", "date": "18-02-2019 12:12", "retweet": 0, "like": 0}]