[{"id": "1099342983592198145", "url": "https://twitter.com/sasi_gg/status/1099342983592198145", "username": "", "text": "ง่วงๆ อยู่ตื่นเต็มตาเรย pic.twitter.com/zaDSAdHFsV", "date": "23-02-2019 23:19", "retweet": 0, "like": 4}, {"id": "1099341623853428736", "url": "https://twitter.com/sasi_gg/status/1099341623853428736", "username": "", "text": "เดี๋ยวรอเปลี่ยนหมึกพิมพ์ก่อน เสื้อพี่มินโฮเราจะเผยโฉม", "date": "23-02-2019 23:14", "retweet": 0, "like": 0}, {"id": "1099332079328743425", "url": "https://twitter.com/sasi_gg/status/1099332079328743425", "username": "", "text": "คิดถึงพี่คยองชิกจัง แต่ย้ายค่ายไปซะแล้ว", "date": "23-02-2019 22:36", "retweet": 0, "like": 0}, {"id": "1099314652599570432", "url": "https://twitter.com/sasi_gg/status/1099314652599570432", "username": "", "text": "รบกวนเมนชั่นมาด้วยได้ไหมคะ", "date": "23-02-2019 21:26", "retweet": 0, "like": 0}, {"id": "1099313031626932226", "url": "https://twitter.com/sasi_gg/status/1099313031626932226", "username": "", "text": "กรี๊ดดดดดดด", "date": "23-02-2019 21:20", "retweet": 0, "like": 0}, {"id": "1099312786469863425", "url": "https://twitter.com/sasi_gg/status/1099312786469863425", "username": "", "text": "อันนี้มีคนจองไหมคะ ถ้าไม่มีจองค่ะ pic.twitter.com/E3nUIWcYhc", "date": "23-02-2019 21:19", "retweet": 0, "like": 0}, {"id": "1099308483885690880", "url": "https://twitter.com/sasi_gg/status/1099308483885690880", "username": "", "text": "เห็นที่ไหนอีกก็ทักมานะคะ จะรวมไว้ใน reply ทวิตด้านล่างนี้ #Best_CHOIs_MINHOinBKK https:// twitter.com/sasi_gg/status /1099306570188378117 …", "date": "23-02-2019 21:02", "retweet": 0, "like": 0}, {"id": "1099308178829758467", "url": "https://twitter.com/sasi_gg/status/1099308178829758467", "username": "", "text": "แจก 5 รางวัล รางวัลละ 2 ใบ ไม่ระบุบัตร ทำกิจกรรมตามเงื่อนไขใน Facebook ประกาศผล 28 ก.พ. #Best_CHOIs_MINHOinBKK https:// twitter.com/Sanook/status/ 1098873378952306688?s=19 …", "date": "23-02-2019 21:01", "retweet": 13, "like": 4}, {"id": "1099307367882055680", "url": "https://twitter.com/sasi_gg/status/1099307367882055680", "username": "", "text": "ลุ้นรับบัตร หลายราคาตามเงื่อนไข ประกาศผล 1 มี.ค. #Best_CHOIs_MINHOinBKK https:// twitter.com/sasi_gg/status /1098487659268198400?s=19 …", "date": "23-02-2019 20:57", "retweet": 11, "like": 3}, {"id": "1099307024586690560", "url": "https://twitter.com/sasi_gg/status/1099307024586690560", "username": "", "text": "ลุ้นบัตร 4500 บาท 10 ใบ ประกาศผล 26 ก.พ. นี้ เงื่อนไขอ่านในทวิตเตอร์ #Best_CHOIs_MINHOinBKK https:// twitter.com/Korseries/stat us/1099295444499259393?s=19 …", "date": "23-02-2019 20:56", "retweet": 14, "like": 7}, {"id": "1099306570188378117", "url": "https://twitter.com/sasi_gg/status/1099306570188378117", "username": "", "text": "รวมลุ้นรับบัตรจากที่ต่่าง ๆ #Best_CHOIs_MINHOinBKK ดูใน reply จ้า", "date": "23-02-2019 20:54", "retweet": 117, "like": 45}, {"id": "1099301528374894593", "url": "https://twitter.com/sasi_gg/status/1099301528374894593", "username": "", "text": "เขาไม่รับกินคนเดียว", "date": "23-02-2019 20:34", "retweet": 0, "like": 0}, {"id": "1099300492314701824", "url": "https://twitter.com/sasi_gg/status/1099300492314701824", "username": "", "text": "ขอให้ฟิคทุกเรื่องที่อ่านอยู่ อัปเดตตอน อีแทมิน อีแทมิน อีแทมิน", "date": "23-02-2019 20:30", "retweet": 0, "like": 2}, {"id": "1099297396633157632", "url": "https://twitter.com/sasi_gg/status/1099297396633157632", "username": "", "text": "อยากกินอาหารเกาหลีแบบเครื่องเคียงจัดเต็มอะ กรุงเทพฯร้านไหนบ้าง #อร่อยไปเเดก", "date": "23-02-2019 20:18", "retweet": 0, "like": 0}, {"id": "1099281338601885696", "url": "https://twitter.com/sasi_gg/status/1099281338601885696", "username": "", "text": "Amazing Saturday จะไม่มีคีย์บอมแล้ว หวังว่ารายการจะอยู่นานๆ จนออกจากกรม และขอให้คีย์ได้กลับเข้ามาเป็นโฮสด้วย", "date": "23-02-2019 19:14", "retweet": 60, "like": 32}, {"id": "1099277916830031872", "url": "https://twitter.com/sasi_gg/status/1099277916830031872", "username": "", "text": "เตรียตัวใจเต้นเลย", "date": "23-02-2019 19:00", "retweet": 0, "like": 0}, {"id": "1099277341467992064", "url": "https://twitter.com/sasi_gg/status/1099277341467992064", "username": "", "text": "เพิ่มเติมค่ะ หากไม่มีสาขาใกล้บ้าน ซื้อสินค้าได้ แล้วได้ลุ้นเหมือนกัน #Best_CHOIs_MINHOinBKK pic.twitter.com/GqtwcwEIQ4", "date": "23-02-2019 18:58", "retweet": 5, "like": 2}, {"id": "1099275364352679936", "url": "https://twitter.com/sasi_gg/status/1099275364352679936", "username": "", "text": "พี่มินโฮจะร้องเพลงไทยสักเพลงไหมคะ?", "date": "23-02-2019 18:50", "retweet": 9, "like": 2}, {"id": "1099267747962179586", "url": "https://twitter.com/sasi_gg/status/1099267747962179586", "username": "", "text": "อีแทมินแน่นอน", "date": "23-02-2019 18:20", "retweet": 0, "like": 0}, {"id": "1099240710123880448", "url": "https://twitter.com/sasi_gg/status/1099240710123880448", "username": "", "text": "ต่างชาติคนที่เราติดต่อเรื่องบัตรอยู่เขาเข้าใจเรานะคะ เขารู้ว่าเร่ไม่พอใจ และต่างชาติที่ไม่ใช่อินเดียหลายคนก็ทราบอยู่ อีกอย่างเขาให้เราปริ้นกันเองอะ ควไม่มีปัญหา", "date": "23-02-2019 16:33", "retweet": 1, "like": 2}, {"id": "1099188404560879616", "url": "https://twitter.com/sasi_gg/status/1099188404560879616", "username": "", "text": "หือออ แอคออฟชายนี่ ไลค์แอคแฟนคลับด้วยอะ อันอื่นเป็นแอคออฟนะ /มือลั่นเหรอแทมิน/ pic.twitter.com/SstKf9Cm31", "date": "23-02-2019 13:05", "retweet": 98, "like": 33}, {"id": "1099185090280665090", "url": "https://twitter.com/sasi_gg/status/1099185090280665090", "username": "", "text": "รีล่า น่ารักมากเลย ฮือออออ", "date": "23-02-2019 12:52", "retweet": 0, "like": 2}, {"id": "1099172738298667009", "url": "https://twitter.com/sasi_gg/status/1099172738298667009", "username": "", "text": "manners?", "date": "23-02-2019 12:02", "retweet": 0, "like": 0}, {"id": "1099167301687889920", "url": "https://twitter.com/sasi_gg/status/1099167301687889920", "username": "", "text": "คุยกับเพื่อนชนว.ต่างชาติเขาเห็นโปรเจคจากอินเดียแล้วมาถาม บางคนช่วยแชร์ นี่บอกไม่รู้เรื่องเลย ทีมงานไทยยังไม่ประกาศเลย นั่นอินเดียไม่ใช่ไทย เพื่อนเงียบกันหมด โกรธอะ บ้านตัวเองก็ไม่ใช่ ไม่เคยถามด้วยปะ อยากทำคือทำเหรอ", "date": "23-02-2019 11:41", "retweet": 234, "like": 27}, {"id": "1099165839394127872", "url": "https://twitter.com/sasi_gg/status/1099165839394127872", "username": "", "text": "ไปหาแอค ออฟฟิเชียลชาวอลอินเดีย แล้วอ่านดูค่ะ สรุปเองเสร็จสรรพ ให้ทางไทยรีและปริ้นอีก", "date": "23-02-2019 11:35", "retweet": 31, "like": 0}, {"id": "1099145926759727105", "url": "https://twitter.com/sasi_gg/status/1099145926759727105", "username": "", "text": "หน้าด้านอะ", "date": "23-02-2019 10:16", "retweet": 0, "like": 1}, {"id": "1098924923060334592", "url": "https://twitter.com/sasi_gg/status/1098924923060334592", "username": "", "text": "โดยเด็กอ้อนห้ามเปลี่ยนด้อม", "date": "22-02-2019 19:38", "retweet": 4, "like": 8}, {"id": "1098911266351927298", "url": "https://twitter.com/sasi_gg/status/1098911266351927298", "username": "", "text": "ไปบ้านเธอก่อนแล้วค่อยทำนะโปรเจคอะ", "date": "22-02-2019 18:43", "retweet": 1, "like": 0}, {"id": "1098894430143049728", "url": "https://twitter.com/sasi_gg/status/1098894430143049728", "username": "", "text": "ชอบชุดแทมินวันนี้นะ", "date": "22-02-2019 17:37", "retweet": 0, "like": 0}, {"id": "1098885839717691397", "url": "https://twitter.com/sasi_gg/status/1098885839717691397", "username": "", "text": "มีบัตรมาแจกอีกค่าาาา #Best_CHOIs_MINHOinBKK https:// twitter.com/Sanook/status/ 1098873378952306688 …", "date": "22-02-2019 17:02", "retweet": 21, "like": 5}, {"id": "1098885711200022528", "url": "https://twitter.com/sasi_gg/status/1098885711200022528", "username": "", "text": "เก่งมากกกก #WANT2ndwin", "date": "22-02-2019 17:02", "retweet": 2, "like": 0}, {"id": "1098885449458769920", "url": "https://twitter.com/sasi_gg/status/1098885449458769920", "username": "", "text": "ถูกต้อง 100%ค่ะ", "date": "22-02-2019 17:01", "retweet": 0, "like": 1}, {"id": "1098870821546733568", "url": "https://twitter.com/sasi_gg/status/1098870821546733568", "username": "", "text": "#TouchYourHeart น่ารักมากกกกกกกกกกกกกก", "date": "22-02-2019 16:03", "retweet": 0, "like": 2}, {"id": "1098846609050222592", "url": "https://twitter.com/sasi_gg/status/1098846609050222592", "username": "", "text": "น้องชายบ่นใส่ วันๆ ไม่นอน นินดึก นอนเช้า เอาแต่เล่นไลน์ อยากบอกน้องเหลือเกินว่า พี่อ่านจอย ._.", "date": "22-02-2019 14:27", "retweet": 0, "like": 0}, {"id": "1098840196697579521", "url": "https://twitter.com/sasi_gg/status/1098840196697579521", "username": "", "text": "อ่านแล้วไม่ระบุอะ ส่งได้หลายคำตอบมั้ง", "date": "22-02-2019 14:01", "retweet": 0, "like": 0}, {"id": "1098839642843996161", "url": "https://twitter.com/sasi_gg/status/1098839642843996161", "username": "", "text": "ยัยตัวน่ารัก pic.twitter.com/6n308Pf83M", "date": "22-02-2019 13:59", "retweet": 1, "like": 0}, {"id": "1098837804610576386", "url": "https://twitter.com/sasi_gg/status/1098837804610576386", "username": "", "text": "มีใครส่งคำถามให้มินโฮเกี่ยวกับคีย์ปะคะ ถึงขั้นโพสไอจีรูปกำลังจาม / ใช่ค่ะชั้นชิปมินคีย์/", "date": "22-02-2019 13:52", "retweet": 1, "like": 2}, {"id": "1098837507699990533", "url": "https://twitter.com/sasi_gg/status/1098837507699990533", "username": "", "text": "คำถามนี้อาจจะเยอะ คีย์ถึงขั้นอัปไอจีว่าจาม", "date": "22-02-2019 13:50", "retweet": 0, "like": 0}, {"id": "1098836898364026881", "url": "https://twitter.com/sasi_gg/status/1098836898364026881", "username": "", "text": "ตัวอย่างคำถาม จะให้นั่งตักพี่ หรือ นั่งในใจพี่ พี่มินโฮต้องเลือก!!!!!!", "date": "22-02-2019 13:48", "retweet": 26, "like": 13}, {"id": "1098834512769822720", "url": "https://twitter.com/sasi_gg/status/1098834512769822720", "username": "", "text": "ไปส่งคำถามกันนนนน #Best_CHOIs_MINHOinBKK https:// docs.google.com/forms/d/e/1FAI pQLSfcSDcQwQZjMVTbmbDoK_9XduHRaEGhjLoqxkn3VdTSMGGzQA/viewform … pic.twitter.com/3dtEHffQu2", "date": "22-02-2019 13:38", "retweet": 17, "like": 6}, {"id": "1098823454105587713", "url": "https://twitter.com/sasi_gg/status/1098823454105587713", "username": "", "text": "ในขณะที่พี่ใหญ่วงยืนเอามือพาดไหล่พี่คีย์ด้วยหน้ากังวล น้องเล็กของวงก็เอามือทั้งสองข้างจับแขนล่ำน้องมินโฮโยกตัวไปมาเพราะตื่นเต้น pic.twitter.com/8N8ByrnX8Q", "date": "22-02-2019 12:55", "retweet": 221, "like": 84}, {"id": "1098807297399087104", "url": "https://twitter.com/sasi_gg/status/1098807297399087104", "username": "", "text": "ยอดโดเนทอัปเดต 12 ก.พ. 2019 เฉพาะชนว.ไทย (กรณีไม่มี PayPal) = 2,062 บาท ชนว. แต่ละประเทศจะมีแหล่งโอนค่ะ ถ้าใครมี PayPal โอนไปได้ตามรูปที่ 2 หากใครต้องการโดท ดูรายละเอียดได้ที่รูปที่ 3 ค่ะ #Best_CHOIs_MINHOinBKK pic.twitter.com/cULf9jeAdF", "date": "22-02-2019 11:50", "retweet": 16, "like": 4}, {"id": "1098806366683033600", "url": "https://twitter.com/sasi_gg/status/1098806366683033600", "username": "", "text": "แทมินจนตอนนี้เวลาอยู่คนเดียวก็ทำได้ดีนะ มีกากบ้างเล็กน้อย พอมาออกรายการกับพี่คีย์เท่านั้นแหละ กากมากเหมือนเดิม", "date": "22-02-2019 11:47", "retweet": 13, "like": 7}, {"id": "1098630436438175744", "url": "https://twitter.com/sasi_gg/status/1098630436438175744", "username": "", "text": "เรามีแท่งไฟแล้วนะคะ ถามเผื่อคนอื่นเฉยๆ", "date": "22-02-2019 00:08", "retweet": 0, "like": 0}, {"id": "1098628749094924288", "url": "https://twitter.com/sasi_gg/status/1098628749094924288", "username": "", "text": "รีทวิตไปแร้วววว ของเรามีแล้วค่ะ ถามเผื่อคนอื่นเฉยๆ", "date": "22-02-2019 00:01", "retweet": 0, "like": 1}, {"id": "1098624344807268355", "url": "https://twitter.com/sasi_gg/status/1098624344807268355", "username": "", "text": "อยากให้คุณธนาธร หรือพรรค @Thanathorn_FWP ฟ้องมากเลยค่ะ เขาชูเพราะเขตนั้นพรรคเขาเบอร์ 3 pic.twitter.com/w94p5OS6nt", "date": "21-02-2019 23:43", "retweet": 4, "like": 2}, {"id": "1098622476504858624", "url": "https://twitter.com/sasi_gg/status/1098622476504858624", "username": "", "text": "แงง คนลงชื่อเกินสองร้อยคนค่ะ ต้องลุ้นว่าถูกเลือกไหม", "date": "21-02-2019 23:36", "retweet": 0, "like": 0}, {"id": "1098619343951126528", "url": "https://twitter.com/sasi_gg/status/1098619343951126528", "username": "", "text": "[샤이니키] - SHIFT KEY focus 직캠 FANCAM: https:// youtu.be/xRQH7LxtSPg", "date": "21-02-2019 23:23", "retweet": 1, "like": 0}, {"id": "1098619075612176384", "url": "https://twitter.com/sasi_gg/status/1098619075612176384", "username": "", "text": "ใครยังต้องการขายบัตร #Best_CHOIs_MINHOinBKK เมนชั่นมาใต้ทวิตนี้ได้ไหมคะ จะได้อยู่ที่เดียวเลย คนที่มองหาอยู่จะได้จับจองหรือซื้อเลย ระบุที่นั่ง จำนวน วิธีรับ ราคาเต็ม/ลดราคา/ผ่อนบัตร ติดต่อใคร", "date": "21-02-2019 23:22", "retweet": 43, "like": 8}, {"id": "1098618116026687488", "url": "https://twitter.com/sasi_gg/status/1098618116026687488", "username": "", "text": "เพิ่งเห็นว่าจุก.../คร่อก แมวพิมพ์/ pic.twitter.com/p8Wjtoyxuw", "date": "21-02-2019 23:19", "retweet": 0, "like": 1}, {"id": "1098607187872624644", "url": "https://twitter.com/sasi_gg/status/1098607187872624644", "username": "", "text": "เปลี่ยนตาอันนี้แหละ ขายยูเซอรินได้เลย", "date": "21-02-2019 22:35", "retweet": 0, "like": 0}, {"id": "1098570497485230080", "url": "https://twitter.com/sasi_gg/status/1098570497485230080", "username": "", "text": "สวยอะ", "date": "21-02-2019 20:09", "retweet": 0, "like": 0}, {"id": "1098564471209914373", "url": "https://twitter.com/sasi_gg/status/1098564471209914373", "username": "", "text": "เก็บอากาศใส่กล่องไว้ด้วย 55555", "date": "21-02-2019 19:45", "retweet": 0, "like": 0}, {"id": "1098562745371262977", "url": "https://twitter.com/sasi_gg/status/1098562745371262977", "username": "", "text": "แต่เอาเถอะ ถ้ามาพักผ่อนก็เขาให้ได้พักสบายๆ ไร้กังวลนะมินโฮ", "date": "21-02-2019 19:39", "retweet": 19, "like": 8}, {"id": "1098562514885865472", "url": "https://twitter.com/sasi_gg/status/1098562514885865472", "username": "", "text": "จะเข้ากรมแล้วมันมีประเด็นออกนอกประเทศจำกัดปะ ใช่มะ ที่เคยอ่านข่าวอะถ้าจำไม่ผิด มินโฮเลยออกมายาวๆ ทีเดียวแล้วค่อยกลับปะ /ไม่รู้ เดา", "date": "21-02-2019 19:38", "retweet": 12, "like": 2}, {"id": "1098546850179641345", "url": "https://twitter.com/sasi_gg/status/1098546850179641345", "username": "", "text": "รีวิวหลังจากเปลี่ยนธีมเปลี่ยนวอลโทรศัพท์เป็นสีเรียกเงินตามวันเกิด ขายยูเซอรินไปแล้ว 2 ชุด pic.twitter.com/jVk2pJXGZ2", "date": "21-02-2019 18:35", "retweet": 0, "like": 2}, {"id": "1098543627196760064", "url": "https://twitter.com/sasi_gg/status/1098543627196760064", "username": "", "text": "มินโฮน่าจะมาเที่ยว ก่อนเข้ากรมละมั้ง พักผ่อนบ้างก็ดี", "date": "21-02-2019 18:23", "retweet": 9, "like": 5}, {"id": "1098528805981904896", "url": "https://twitter.com/sasi_gg/status/1098528805981904896", "username": "", "text": "เรามีแล้วค่ะ แต่คนไม่มีเยอะมาก เลยอยากลุ้นแทนทุกคน", "date": "21-02-2019 17:24", "retweet": 0, "like": 0}, {"id": "1098521294104981509", "url": "https://twitter.com/sasi_gg/status/1098521294104981509", "username": "", "text": "ไม่แน่ใจว่าสั่งแท่งไฟวันนี้จะทันงานไหม ลองลุ้นดูนะคะ #Best_CHOIs_MINHOinBKK", "date": "21-02-2019 16:54", "retweet": 2, "like": 0}, {"id": "1098518447263105024", "url": "https://twitter.com/sasi_gg/status/1098518447263105024", "username": "", "text": "อยู่หาดใหญ่หรือคะ ตำบลเดียวกันเลยค่ะ", "date": "21-02-2019 16:43", "retweet": 0, "like": 1}, {"id": "1098501070395854850", "url": "https://twitter.com/sasi_gg/status/1098501070395854850", "username": "", "text": "ดีนะ ที่พรีของมินโฮไปแล้ว", "date": "21-02-2019 15:33", "retweet": 0, "like": 0}, {"id": "1098499401402658816", "url": "https://twitter.com/sasi_gg/status/1098499401402658816", "username": "", "text": "คนลงชื่อเมื่อวานเยอะมากค่ะ บางคนหาไม่เจอจริงๆ คนที่หาเจอก็เจอเลยนะ", "date": "21-02-2019 15:27", "retweet": 0, "like": 0}, {"id": "1098492479039463424", "url": "https://twitter.com/sasi_gg/status/1098492479039463424", "username": "", "text": "ให้ชื่อแอคทวิตเตอร์ หรือไอจี ถูกต้องกันแน่ใช่ไหม เพิ่งลงชื่อเมื่อวาน วันนี้ทำการตรวจสอบคือหาแล้วไม่ใช่ชื่อตามที่แจ้งอะ หรือไม่ก็ไอจีล็อคแอคอะ #Best_CHOIs_MINHOinBKK", "date": "21-02-2019 14:59", "retweet": 5, "like": 1}, {"id": "1098487659268198400", "url": "https://twitter.com/sasi_gg/status/1098487659268198400", "username": "", "text": "ลุ้นรับบัตรค่ะ #Best_CHOIs_MINHOinBKK https:// m.facebook.com/story.php?stor y_fbid=2143216469057948&id=259999080713039 … pic.twitter.com/EAHzSZe5Bm", "date": "21-02-2019 14:40", "retweet": 220, "like": 46}, {"id": "1098466934515949569", "url": "https://twitter.com/sasi_gg/status/1098466934515949569", "username": "", "text": "เราต้องเตรียมคนประกันตัวไว้ไหมคะ", "date": "21-02-2019 13:18", "retweet": 0, "like": 1}, {"id": "1098456184757972992", "url": "https://twitter.com/sasi_gg/status/1098456184757972992", "username": "", "text": "ถ้าย้ายที่นั่งรอบนี้ คือย้ายไปบนตักพี่มินโฮแล้ว #Best_CHOIs_MINHOinBKK pic.twitter.com/dYAv8fh3Bg", "date": "21-02-2019 12:35", "retweet": 6, "like": 6}, {"id": "1098453763226927104", "url": "https://twitter.com/sasi_gg/status/1098453763226927104", "username": "", "text": "ใครที่อยู่หลังๆ ก็มานั่งด้วยกันเน้อออ #Best_CHOIs_MINHOinBKK", "date": "21-02-2019 12:26", "retweet": 5, "like": 0}, {"id": "1098451915212378112", "url": "https://twitter.com/sasi_gg/status/1098451915212378112", "username": "", "text": "#Best_CHOIs_MINHOinBKK ประกาศการย้ายที่นั่ง ในโซนเดิม ราคาเดิม เท่านั้น!!! ตั้งแต่ตอนนี้ ถึงวันที่ 21 ก.พ. 2562 (คืนนี้!!!) เวลา 22.00 น. Seat Change Request open!!! in the same zone same price only!!! ONLY from NOW till 21th Feb , 10.00 PM https://www. facebook.com/CHOIMINHOFANME ETINGTOURINBKK/posts/271904707078980 … pic.twitter.com/JUxLraqFDD", "date": "21-02-2019 12:18", "retweet": 71, "like": 10}, {"id": "1098244197981671426", "url": "https://twitter.com/sasi_gg/status/1098244197981671426", "username": "", "text": "มินโฮไหน", "date": "20-02-2019 22:33", "retweet": 0, "like": 1}, {"id": "1098227493859778561", "url": "https://twitter.com/sasi_gg/status/1098227493859778561", "username": "", "text": "ก็ยังดีอะ", "date": "20-02-2019 21:26", "retweet": 0, "like": 0}, {"id": "1098227086659973120", "url": "https://twitter.com/sasi_gg/status/1098227086659973120", "username": "", "text": "ใช่ แทมินยื่นให้ด้วย", "date": "20-02-2019 21:25", "retweet": 0, "like": 0}, {"id": "1098166123650965504", "url": "https://twitter.com/sasi_gg/status/1098166123650965504", "username": "", "text": "ลูกแมมมมมม่ #Want1stWin", "date": "20-02-2019 17:23", "retweet": 0, "like": 1}, {"id": "1098105284860403712", "url": "https://twitter.com/sasi_gg/status/1098105284860403712", "username": "", "text": "Viu มี #RomanceisaBonusBook ปะ", "date": "20-02-2019 13:21", "retweet": 0, "like": 0}, {"id": "1097897706423349248", "url": "https://twitter.com/sasi_gg/status/1097897706423349248", "username": "", "text": "พอเปลี่ยนสีวอลเปเปอร์โทรศัพท์เป็นสีเรียกเงิน ก็ขายยูเซอรินเซตนี้ได้เลย ยังมีอยู่นะคะ สนใจบอกได้ pic.twitter.com/SEFDTyawO3", "date": "19-02-2019 23:36", "retweet": 0, "like": 1}, {"id": "1097891998348898304", "url": "https://twitter.com/sasi_gg/status/1097891998348898304", "username": "", "text": "ขาแทมินเทียบกับแดนเซอร์แล้วเล็กมาก pic.twitter.com/GEsgdiZ5dV", "date": "19-02-2019 23:13", "retweet": 37, "like": 24}, {"id": "1097871698706104320", "url": "https://twitter.com/sasi_gg/status/1097871698706104320", "username": "", "text": "ยอดโดเนทอัปเดต 19 ก.พ. 2019 เฉพาะชนว.ไทย (กรณีไม่มี PayPal) = 1,982 บาท ชนว. แต่ละประเทศจะมีแหล่งโอนค่ะ ถ้าใครมี PayPal โอนไปได้ตามรูปที่ 2 หากใครต้องการโดท ดูรายละเอียดได้ที่รูปที่ 3 ค่ะ #Best_CHOIs_MINHOinBKK pic.twitter.com/cULf9jeAdF", "date": "19-02-2019 21:53", "retweet": 32, "like": 7}, {"id": "1097861951521050625", "url": "https://twitter.com/sasi_gg/status/1097861951521050625", "username": "", "text": "ถ้าปรับแสงดวงจันทร์จะขาว แต่ที่มองเห็นด้วยตาเปล่าจะออกเหลือง pic.twitter.com/apjpORr2Kx", "date": "19-02-2019 21:14", "retweet": 14, "like": 8}, {"id": "1097850939350773761", "url": "https://twitter.com/sasi_gg/status/1097850939350773761", "username": "", "text": "อยู่บนนั่นใช่ป่าว pic.twitter.com/mB4YjL2JhB", "date": "19-02-2019 20:30", "retweet": 12, "like": 7}, {"id": "1097844197594324993", "url": "https://twitter.com/sasi_gg/status/1097844197594324993", "username": "", "text": "@realjonghyun90 คิดถึงกันใช่ป่าว ถึงได้สว่างสดใสขนาดนี้ pic.twitter.com/MqwEyTbG1u", "date": "19-02-2019 20:03", "retweet": 0, "like": 0}, {"id": "1097832380117577728", "url": "https://twitter.com/sasi_gg/status/1097832380117577728", "username": "", "text": "ตอนนี้อาจจะกำลังดีก็ได้ เอส 26 อาจจะผอมไป", "date": "19-02-2019 19:16", "retweet": 0, "like": 0}, {"id": "1097830597588791297", "url": "https://twitter.com/sasi_gg/status/1097830597588791297", "username": "", "text": "อ้วนยังไง", "date": "19-02-2019 19:09", "retweet": 0, "like": 0}, {"id": "1097829158875361280", "url": "https://twitter.com/sasi_gg/status/1097829158875361280", "username": "", "text": "eat bin hill", "date": "19-02-2019 19:04", "retweet": 0, "like": 0}, {"id": "1097823024617730048", "url": "https://twitter.com/sasi_gg/status/1097823024617730048", "username": "", "text": "เหมือนเด็กม.ปลายที่ชอบมีเรื่องชกต่อยอะ pic.twitter.com/yqkdiOUaYj", "date": "19-02-2019 18:39", "retweet": 0, "like": 0}, {"id": "1097821689298087936", "url": "https://twitter.com/sasi_gg/status/1097821689298087936", "username": "", "text": "5555555 แต่อีก 2 ปีอะ ดวงมันเปลี่ยนได้", "date": "19-02-2019 18:34", "retweet": 0, "like": 0}, {"id": "1097813683256709122", "url": "https://twitter.com/sasi_gg/status/1097813683256709122", "username": "", "text": "ทุกรายการที่แทมินไปออก จะมีการตัดภาพ/คลิป หรือพี่ถึงพี่คีย์ เรือ #เด็กผีที่รักเธอ #แทคีย์ แล่นมาก pic.twitter.com/OvQAn6T2L5", "date": "19-02-2019 18:02", "retweet": 1, "like": 1}, {"id": "1097805355063496704", "url": "https://twitter.com/sasi_gg/status/1097805355063496704", "username": "", "text": "ชอบฟังเพลง B.A.P. มากอะ เสียใจ", "date": "19-02-2019 17:29", "retweet": 0, "like": 0}, {"id": "1097801819412025345", "url": "https://twitter.com/sasi_gg/status/1097801819412025345", "username": "", "text": "ร้องห้ายยยยย กรี๊ดดดดดดดดดด pic.twitter.com/zoD61O1unJ", "date": "19-02-2019 17:15", "retweet": 14, "like": 8}, {"id": "1097801288987795456", "url": "https://twitter.com/sasi_gg/status/1097801288987795456", "username": "", "text": "ใช่ค่ะ ต้องให้รัฐจัดการว่าจะทำอย่างไรให้บุคคลากรการแพทย์ในปัจจุบัน กระจายไปยังร.พ.มากขึ้น และอยู่นานขึ้น รวมถึงลดภาระงานโดยการทำให้ประชาชนใส่ใจสุขภาพมากขึ้น การผลิตเพิ่มตอนนี้อย่างน้อย 4-6 ปี ถึงจะเรียนจบขั้นต้นค่ะ", "date": "19-02-2019 17:13", "retweet": 0, "like": 0}, {"id": "1097774800347361280", "url": "https://twitter.com/sasi_gg/status/1097774800347361280", "username": "", "text": "เป็นส่วนหนึ่งค่ะ ส่วนที่เหลือจะเป็นความคิดเห็นส่วนตัวของบุคลากรการแพทย์แต่ละท่านด้วย ซึ่งประสบการณ์ที่พบเจอไม่เหมือนกัน", "date": "19-02-2019 15:28", "retweet": 1, "like": 0}, {"id": "1097773659937095680", "url": "https://twitter.com/sasi_gg/status/1097773659937095680", "username": "", "text": "การให้ความรู้ประชาชนด้านสุขภาพที่ถูกต้อง และทำให้ประชนตระหนักรู้ปละเข้าใจจริงๆ และสามารถช่วยเหลือตัวเองเบื้องต้นได้ เป็นการแก้ปัญหาที่ต้นเหตุได้ส่วนนึงค่ะ", "date": "19-02-2019 15:23", "retweet": 2, "like": 1}, {"id": "1097771767844622336", "url": "https://twitter.com/sasi_gg/status/1097771767844622336", "username": "", "text": "เซิร์ชชื่อพรรคตอบทวิตแน่ๆ pic.twitter.com/mDstyPVnPy", "date": "19-02-2019 15:15", "retweet": 0, "like": 0}, {"id": "1097770743566196736", "url": "https://twitter.com/sasi_gg/status/1097770743566196736", "username": "", "text": "ที่จบจากมหาวิทยาลัยปล้วแน่นอน เยอะมากค่ะ แต่ตำแหน่งที่รัฐรับมีจำกัด และบางส่วนที่เข้าไปทำงานโรงพยาบาล ทำงานหนัก เสี่ยงถูกฟ้อง เลยออกมาอยู่เอกชนกันที่ให้ผลตอบแทนดีกว่าค่ะ", "date": "19-02-2019 15:11", "retweet": 1, "like": 0}, {"id": "1097767867112513537", "url": "https://twitter.com/sasi_gg/status/1097767867112513537", "username": "", "text": "ในฐานะบุคคลากรทางการแพทย์ ทั้งครอบครัว ไม่โอเค ตัด #พรรคเพื่อไทย ออกก่อนเลย ต่อด้วยตัด #พรรคประชารัฐ บอกรัฐบาลนะจ่ายเงินเดือนให้ครบก่อน #พรรคประชาธิปัตย์ สำรวจจำนวนจริงๆ แล้วยัง #พรรคอนาคตใหม่ แน่ใจแล้วนะคะ #เลือกตั้ง62 https:// m.facebook.com/DramaAdd/photo s/a.411063588290/10157283891913291/?type=3&theater … pic.twitter.com/6OQWF0AB3R", "date": "19-02-2019 15:00", "retweet": 13, "like": 3}, {"id": "1097763798054711297", "url": "https://twitter.com/sasi_gg/status/1097763798054711297", "username": "", "text": "หมอดูบอกว่าจะได้แต่งงานตอนอายุ 31 (อีก 2 ปีเท่านั้น) มาดูซิ จะได้หรือไม่ 55555555", "date": "19-02-2019 14:44", "retweet": 1, "like": 3}, {"id": "1097757968794144775", "url": "https://twitter.com/sasi_gg/status/1097757968794144775", "username": "", "text": "คุณคิด พรรคเสรีรวมไทย ดูเป็นคนอารมณ์ดีนะ", "date": "19-02-2019 14:21", "retweet": 2, "like": 1}, {"id": "1097750020860694528", "url": "https://twitter.com/sasi_gg/status/1097750020860694528", "username": "", "text": "สารภาพว่า บางทีก็แอปส่องแฟนบอยแทมิน pic.twitter.com/s4hiyInkOH", "date": "19-02-2019 13:49", "retweet": 3, "like": 3}, {"id": "1097517030306017281", "url": "https://twitter.com/sasi_gg/status/1097517030306017281", "username": "", "text": "ชอบท่าเดินคีย์บอมมาก", "date": "18-02-2019 22:23", "retweet": 0, "like": 1}, {"id": "1097516585130983424", "url": "https://twitter.com/sasi_gg/status/1097516585130983424", "username": "", "text": "อยากให้พี่หงิใส่แว่นอีกนิดอะ ภาพลักษณ์บทตอนนี้เหมือนเด็กม.ปลาย้ลย", "date": "18-02-2019 22:21", "retweet": 0, "like": 1}, {"id": "1097511361733550081", "url": "https://twitter.com/sasi_gg/status/1097511361733550081", "username": "", "text": "แข็งหมดแล้วคีย์บอมเอ้ย", "date": "18-02-2019 22:01", "retweet": 0, "like": 0}, {"id": "1097509859681918979", "url": "https://twitter.com/sasi_gg/status/1097509859681918979", "username": "", "text": "เช็คดีเอ็มกันด้วยจ้าาา ตัดสิทธิ์กันหลายรายแล้ววว #Best_CHOIs_MINHOinBKK ตปท.เขาเลือก แล้วส่งมาให้ติดต่อ เพราะไม่ตอบกันหลายคน ไม่เปิดแอค ไม่เปิดดีเอ็ม ตอนแรกเขาใจดีอยู่ รอได้ แต่ตอนนี้กฎเขาก็เข้มขึ้นเรื่อยๆ นะ เข้าใจทางผู้ให้ด้วยนะคะ", "date": "18-02-2019 21:55", "retweet": 51, "like": 14}, {"id": "1097503599599337474", "url": "https://twitter.com/sasi_gg/status/1097503599599337474", "username": "", "text": "ทีเซอร์น้องคีย์จะมามั้ยคืนนี้", "date": "18-02-2019 21:30", "retweet": 0, "like": 2}, {"id": "1097495221288325121", "url": "https://twitter.com/sasi_gg/status/1097495221288325121", "username": "", "text": "แทมินทำท่าค้างไว้ให้เอาไปทำมีม ออออหหหห", "date": "18-02-2019 20:57", "retweet": 1, "like": 0}, {"id": "1097494405726973953", "url": "https://twitter.com/sasi_gg/status/1097494405726973953", "username": "", "text": "มันเหมือนตรงไหน pic.twitter.com/a95aMpKLyw", "date": "18-02-2019 20:53", "retweet": 8, "like": 2}, {"id": "1097493649774936065", "url": "https://twitter.com/sasi_gg/status/1097493649774936065", "username": "", "text": "ที่ขำคือ รูปที่ส่งในแชทรูม 95% เป็นมีมแทมินเอง", "date": "18-02-2019 20:50", "retweet": 0, "like": 1}, {"id": "1097490594950111234", "url": "https://twitter.com/sasi_gg/status/1097490594950111234", "username": "", "text": "แทมิน: ดีมาก เพอเฟค ผมวาดรูปเก่งนะเนี่ย แทมิน: ผมวาดรูปออกจะเหมือน ทำไมทายกันไม่ได้ จ้าาา", "date": "18-02-2019 20:38", "retweet": 37, "like": 14}, {"id": "1097488838908243969", "url": "https://twitter.com/sasi_gg/status/1097488838908243969", "username": "", "text": "ยังกล้าบอกอีกว่า ผมว่าผมวาดรูปได้ดีมากนะ ทำไมแฟนทายกันไม่ได้อ่า เหอ แทมิน", "date": "18-02-2019 20:31", "retweet": 7, "like": 3}, {"id": "1097488546703671296", "url": "https://twitter.com/sasi_gg/status/1097488546703671296", "username": "", "text": "เกลียดรูปที่แทมินวาดมากบอกตง 555555555555555555555555", "date": "18-02-2019 20:30", "retweet": 0, "like": 1}, {"id": "1097484268073148416", "url": "https://twitter.com/sasi_gg/status/1097484268073148416", "username": "", "text": "555555555 pic.twitter.com/bcJsVNvQbz", "date": "18-02-2019 20:13", "retweet": 2, "like": 3}, {"id": "1097476205081550849", "url": "https://twitter.com/sasi_gg/status/1097476205081550849", "username": "", "text": "ติดต่อส่วนตัวรายบุคคลแล้วค่ะ ทางทีมต่างประเทศเป็นคนเลือกค่ะ", "date": "18-02-2019 19:41", "retweet": 0, "like": 0}, {"id": "1097466585025937408", "url": "https://twitter.com/sasi_gg/status/1097466585025937408", "username": "", "text": "@SHINee อัปข่าวพี่ิอนยูด้วยค่ะ", "date": "18-02-2019 19:03", "retweet": 7, "like": 1}, {"id": "1097456979314798593", "url": "https://twitter.com/sasi_gg/status/1097456979314798593", "username": "", "text": "โฟกัสอยู่ตำแหน่งเดียวเลย pic.twitter.com/rDBmzh8oQg", "date": "18-02-2019 18:25", "retweet": 18, "like": 7}, {"id": "1097456654751133696", "url": "https://twitter.com/sasi_gg/status/1097456654751133696", "username": "", "text": "เนี่ย ตากล้องถึงขั้นถ่ายฉากนี้ ไม่เห็นแทมิน https:// twitter.com/sasi_gg/status /1097434622781059072 …", "date": "18-02-2019 18:23", "retweet": 1, "like": 1}, {"id": "1097443827252527104", "url": "https://twitter.com/sasi_gg/status/1097443827252527104", "username": "", "text": "ดูคลิปซ้อมเต้นแทมินแล้วยัง", "date": "18-02-2019 17:32", "retweet": 0, "like": 0}, {"id": "1097436098903433216", "url": "https://twitter.com/sasi_gg/status/1097436098903433216", "username": "", "text": "เห็นว่าเป็นเทรนนี่ค่ะ เอสเอ็มดันสุด คือถ้านิดๆ หน่อยๆ อะน่าสนใจมากนะ แต่นี่เกินไปแล้ว", "date": "18-02-2019 17:02", "retweet": 0, "like": 1}, {"id": "1097434622781059072", "url": "https://twitter.com/sasi_gg/status/1097434622781059072", "username": "", "text": "เพื่ออะไร อะฉากนี้ ? pic.twitter.com/Rr8TcurQFq", "date": "18-02-2019 16:56", "retweet": 36, "like": 3}, {"id": "1097434112112058371", "url": "https://twitter.com/sasi_gg/status/1097434112112058371", "username": "", "text": "อันก่อนพิมพ์ผิดเยอะ อารมณ์บ่จอยพิมพ์ใหม่", "date": "18-02-2019 16:54", "retweet": 0, "like": 0}, {"id": "1097421847711252480", "url": "https://twitter.com/sasi_gg/status/1097421847711252480", "username": "", "text": "ทำไมแทมินไม่สระผมอะคะ เดี๋ยวเหากลับมาอีกนะ", "date": "18-02-2019 16:05", "retweet": 0, "like": 2}, {"id": "1097400292511952896", "url": "https://twitter.com/sasi_gg/status/1097400292511952896", "username": "", "text": "@SHINee ไม่ทวิตเรื่องมิวสิคเคิลพี่อนยูเหรอคะ ค่ายอื่นเขาทำกันนะ", "date": "18-02-2019 14:39", "retweet": 0, "like": 0}, {"id": "1097398401342164992", "url": "https://twitter.com/sasi_gg/status/1097398401342164992", "username": "", "text": "ปริญญาตรี เลือกอะไรดี วจก. บริหารธุรกิจ vs ศศ.บ. เอกภาษาอังกฤษ คือจะเรียนทั้ง 2 อย่างอะ แต่เลือกเรียนทีละอย่าง", "date": "18-02-2019 14:32", "retweet": 0, "like": 0}, {"id": "1097391101437079554", "url": "https://twitter.com/sasi_gg/status/1097391101437079554", "username": "", "text": "พี่อนยูขาของหนู๊", "date": "18-02-2019 14:03", "retweet": 0, "like": 0}, {"id": "1097374467343306752", "url": "https://twitter.com/sasi_gg/status/1097374467343306752", "username": "", "text": "เพียงแค่เปิดดูรูป ก็ยิ้มได้ทั้งปาก ทั้งตา ทั้งใจ pic.twitter.com/DrJgDKnGEy", "date": "18-02-2019 12:57", "retweet": 10, "like": 8}]